auvio/__init__.py
auvio/main.py
auvio-1.0.4.dist-info/LICENSE
auvio-1.0.4.dist-info/METADATA
auvio-1.0.4.dist-info/WHEEL
auvio-1.0.4.dist-info/top_level.txt
auvio-1.0.4.dist-info/RECORD
